{
  "settings": {
    "migrated": true,
    "iconPacksPath": "plugins/obsidian-icon-folder/icons",
    "fontSize": 16,
    "iconColor": null,
    "recentlyUsedIcons": [
      "RiLayout3Fill",
      "FarNewspaper",
      "FarFaceMehBlank",
      "RiMagicFill",
      "RiLayoutTop2Fill"
    ],
    "recentlyUsedIconsSize": 5,
    "rules": [],
    "extraPadding": {
      "top": 2,
      "right": 2,
      "bottom": 2,
      "left": 2
    }
  },
  "Welten/Deseria/1. Stories/Das Begraebnis": "RiKnifeBloodLine",
  "Welten/Deseria/1. Stories": "FarNewspaper",
  "Welten/Deseria": "RiLayout3Fill",
  "Welten/Deseria/1. Stories/Das Begraebnis/Notizen": "RiEditFill",
  "Welten/Deseria/2. Figuren": "RiParentLine",
  "Welten/Deseria/4. Locations": "RiMapPin2Fill",
  "Welten/Deseria/3. Events und Ereignisse": "FarClock",
  "Welten/Deseria/5. Details": "FarLightbulb",
  "Welten/Deseria/6. Sideinfo": "RiArticleLine",
  "Welten/Deseria/88. Spiel": "RiGamepadFill",
  "Welten/templates": "RiFileTextLine",
  "Downloads": "RiDownload2Line",
  "charactermaker": "FarPenToSquare",
  "Welten/Deseria/99._Attachements": "RiAttachment2",
  "groupchat": "RiChat1Line",
  "Welten": "RiGlobeFill",
  "Welten/Deseria/3. Events und Ereignisse/DSDSH.md": "RiSwordFill",
  "Welten/Deseria/3. Events und Ereignisse/Prozession des heiligen Hasen.md": "RiVipCrownFill",
  "Welten/Deseria/1. Stories/Das Begraebnis/Notizen/Plot.md": "RiLayoutTop2Fill",
  "Welten/Deseria/1. Stories/GENERATOR.md": "RiMagicFill",
  "Welten/Deseria/2. Figuren/GENERATOR.md": "RiMagicFill",
  "Welten/Deseria/3. Events und Ereignisse/GENERATOR.md": "RiMagicFill",
  "Welten/Deseria/4. Locations/GENERATOR.md": "RiMagicFill",
  "Welten/Deseria/5. Details/Gegenstände/GENERATOR.md": "RiMagicFill",
  "Welten/Deseria/5. Details/Resourcen und Materialien/GENERATOR.md": "RiMagicFill"
}